saug/__init__.py
saug/saug.py
saug-0.0.5.dist-info/METADATA
saug-0.0.5.dist-info/WHEEL
saug-0.0.5.dist-info/licenses/LICENSE.txt
saug-0.0.5.dist-info/RECORD
