Metadata-Version: 2.3
Name: saug
Version: 0.0.5
Summary: Spatial distortions for image augmentations
Project-URL: Homepage, https://github.com/SoroushOskouei/saug
Author-email: Soroush Oskouei <sorush7oskouee@gmail.com>
License-File: LICENSE.txt
Classifier: License :: OSI Approved :: MIT License
Classifier: Operating System :: OS Independent
Classifier: Programming Language :: Python :: 3
Requires-Python: >=3.8
